part_2_digital_comps/algorithm/verilog/sar_logic.v
module sar_logic (
    input wire clk, 
    input wire Op,
    input wire En,
    input wire Om,
    input wire rst,
    output reg [6:0] B,   // 7-bit
    output reg [6:0] BN,  // 7-bit
    output reg [7:0] D    // 8-bit
);

reg [3:0] counter = 4'b0000; // 4-bit counter

always @(posedge clk) begin
    if (rst) begin
        B <= 7'b0000000;
        BN <= 7'b0000000;
        D <= 8'b00000000;
        counter <= 4'b0000;
    end else if (En && (Op ^ Om)) begin
        if (counter < 7) begin 
            D <= D | ({7'b0, Op} << counter);
              
            B[counter % 7] <= (Op) ? 1'b1 : 1'b0;
            BN[counter % 7] <= (Om) ? 1'b1 : 1'b0;

            counter <= counter + 1'b1;
        end
    end
end

endmodule

part_2_digital_comps/algorithm/verilog/sar_logic_tb.v
`timescale 1ns/1ps

module sar_logic_tb();

    // Inputs
    reg clk;
    reg rst;
    reg Op;
    reg Om;
    reg En;

    // Outputs
    wire [6:0] B;
    wire [6:0] BN;
    wire [7:0] D;

    // Instantiate the SAR Logic module
    sar_logic uut (
        .clk(clk),
        .rst(rst),
        .Op(Op),
        .Om(Om),
        .En(En),
        .B(B),
        .BN(BN),
        .D(D)
    );

    // Clock generation
    always #5 clk = ~clk;

    // Test sequence
    initial begin
        $dumpfile("sar_logic_tb.vcd");  // Name of the VCD file
        $dumpvars(0, sar_logic_tb);     // Dump all variables in the testbench

        // Initialize inputs
        clk = 1'b0;
        rst = 1'b1;
        Op = 1'b0;
        Om = 1'b0;
        En = 1'b0;

        // Apply reset
        #20 rst = 1'b0;
        En = 1'b1;
        Op = 1'b1;
        Om = 1'b0;
        
        // Apply reset again
        #80 rst = 1'b1;
        #10 rst = 1'b0;
        Op = 1'b0;
        Om = 1'b1;

        #70 rst = 1'b1;

        // End of simulation
        #100 $finish;
    end

endmodule

part_2_digital_comps/algorithm/verilog/sar_logic_tb.vcd
$date
	Mon Feb  2 08:01:07 2026
$end
$version
	Icarus Verilog
$end
$timescale
	1ps
$end
$scope module sar_logic_tb $end
$var wire 8 ! D [7:0] $end
$var wire 7 " BN [6:0] $end
$var wire 7 # B [6:0] $end
$var reg 1 $ En $end
$var reg 1 % Om $end
$var reg 1 & Op $end
$var reg 1 ' clk $end
$var reg 1 ( rst $end
$scope module uut $end
$var wire 1 $ En $end
$var wire 1 % Om $end
$var wire 1 & Op $end
$var wire 1 ' clk $end
$var wire 1 ( rst $end
$var reg 7 ) B [6:0] $end
$var reg 7 * BN [6:0] $end
$var reg 8 + D [7:0] $end
$var reg 4 , counter [3:0] $end
$upscope $end
$upscope $end
$enddefinitions $end
$comment Show the parameter values. $end
$dumpall
$end
#0
$dumpvars
b0 ,
bx +
bx *
bx )
1(
0'
0&
0%
0$
bx #
bx "
bx !
$end
#5000
b0 !
b0 +
b0 "
b0 *
b0 #
b0 )
1'
#10000
0'
#15000
1'
#20000
0'
1&
1$
0(
#25000
b1 ,
b1 #
b1 )
b1 !
b1 +
1'
#30000
0'
#35000
b10 ,
b11 #
b11 )
b11 !
b11 +
1'
#40000
0'
#45000
b11 ,
b111 #
b111 )
b111 !
b111 +
1'
#50000
0'
#55000
b100 ,
b1111 #
b1111 )
b1111 !
b1111 +
1'
#60000
0'
#65000
b101 ,
b11111 #
b11111 )
b11111 !
b11111 +
1'
#70000
0'
#75000
b110 ,
b111111 #
b111111 )
b111111 !
b111111 +
1'
#80000
0'
#85000
b111 ,
b1111111 #
b1111111 )
b1111111 !
b1111111 +
1'
#90000
0'
#95000
1'
#100000
0'
1(
#105000
b0 ,
b0 !
b0 +
b0 #
b0 )
1'
#110000
0'
1%
0&
0(
#115000
b1 ,
b1 "
b1 *
1'
#120000
0'
#125000
b10 ,
b11 "
b11 *
1'
#130000
0'
#135000
b11 ,
b111 "
b111 *
1'
#140000
0'
#145000
b100 ,
b1111 "
b1111 *
1'
#150000
0'
#155000
b101 ,
b11111 "
b11111 *
1'
#160000
0'
#165000
b110 ,
b111111 "
b111111 *
1'
#170000
0'
#175000
b111 ,
b1111111 "
b1111111 *
1'
#180000
0'
1(
#185000
b0 ,
b0 "
b0 *
1'
